{
  "categories": [
    {
      "category": "名詞：教育・学問・研究・心理（N1補充）",
      "entries": [
        {
          "word": "中退",
          "kana": "ちゅうたい",
          "romaji": "chuutai",
          "pos": "名／動III",
          "zh": "輟學；肄業",
          "ex": "彼（かれ）は経済的（けいざいてき）な事情（じじょう）で大学（だいがく）を中退（ちゅうたい）した。",
          "ex_zh": "他因經濟因素從大學輟學了。"
        },
        {
          "word": "予感",
          "kana": "よかん",
          "romaji": "yokan",
          "pos": "名／動III",
          "zh": "預感",
          "ex": "何（なに）か悪（わる）いことが起（お）こりそうな予感（よかん）がしてならない。",
          "ex_zh": "總覺得會發生什麼壞事,這種預感揮之不去。"
        },
        {
          "word": "修士",
          "kana": "しゅうし",
          "romaji": "shuushi",
          "pos": "名",
          "zh": "碩士",
          "ex": "彼女（かのじょ）は来春（らいしゅん）、修士課程（しゅうしかてい）を修了（しゅうりょう）する予定（よてい）だ。",
          "ex_zh": "她預計明年春天完成碩士課程。"
        },
        {
          "word": "修得",
          "kana": "しゅうとく",
          "romaji": "shuutoku",
          "pos": "名／動III",
          "zh": "學會；習得(知識或技能)",
          "ex": "専門的（せんもんてき）な知識（ちしき）を修得（しゅうとく）するには年月（ねんげつ）がかかる。",
          "ex_zh": "要學會專業知識需要花費歲月。"
        },
        {
          "word": "偏執",
          "kana": "へんしゅう",
          "romaji": "henshuu",
          "pos": "名",
          "zh": "偏執；固執己見",
          "ex": "彼（かれ）の偏執的（へんしゅうてき）な性格（せいかく）が周囲（しゅうい）を疲弊（ひへい）させる。",
          "ex_zh": "他偏執的性格讓周圍的人疲憊不堪。"
        },
        {
          "word": "停学",
          "kana": "ていがく",
          "romaji": "teigaku",
          "pos": "名",
          "zh": "停學",
          "ex": "校則違反（こうそくいはん）で一週間（いっしゅうかん）の停学処分（ていがくしょぶん）を受（う）けた。",
          "ex_zh": "因違反校規而被處以一週停學處分。"
        },
        {
          "word": "卓見",
          "kana": "たっけん",
          "romaji": "takken",
          "pos": "名",
          "zh": "卓見；高見",
          "ex": "その若手研究者（わかてけんきゅうしゃ）の卓見（たっけん）には教授陣（きょうじゅじん）も舌（した）を巻（ま）いた。",
          "ex_zh": "那位年輕研究者的卓見讓教授們都嘆為觀止。"
        },
        {
          "word": "口頭試問",
          "kana": "こうとうしもん",
          "romaji": "koutoushimon",
          "pos": "名",
          "zh": "口試",
          "ex": "博士論文（はくしろんぶん）の口頭試問（こうとうしもん）で厳（きび）しい質問（しつもん）が相次（あいつ）いだ。",
          "ex_zh": "在博士論文的口試中,接連被問到嚴厲的問題。"
        },
        {
          "word": "啓発",
          "kana": "けいはつ",
          "romaji": "keihatsu",
          "pos": "名／動III",
          "zh": "啟發",
          "ex": "この講演（こうえん）は多（おお）くの学生（がくせい）に啓発（けいはつ）を与（あた）えた。",
          "ex_zh": "這場演講啟發了許多學生。"
        },
        {
          "word": "固執",
          "kana": "こしつ",
          "romaji": "koshitsu",
          "pos": "名／動III",
          "zh": "固執；堅持己見",
          "ex": "彼（かれ）は自分（じぶん）の意見（いけん）に固執（こしつ）して譲（ゆず）ろうとしない。",
          "ex_zh": "他固執己見,不肯讓步。"
        },
        {
          "word": "堪能",
          "kana": "たんのう",
          "romaji": "tannou",
          "pos": "な形",
          "zh": "精通；擅長",
          "ex": "彼女（かのじょ）は数（すう）か国語（こくご）に堪能（たんのう）で、通訳（つうやく）としても活躍（かつやく）している。",
          "ex_zh": "她精通好幾國語言,也活躍於口譯工作。"
        },
        {
          "word": "学徒",
          "kana": "がくと",
          "romaji": "gakuto",
          "pos": "名",
          "zh": "求學者；學子(治學之人)",
          "ex": "学徒（がくと）たちは厳（きび）しい師（し）の下（もと）で学問（がくもん）に励（はげ）んだ。",
          "ex_zh": "學子們在嚴師門下勤奮治學。"
        },
        {
          "word": "学業",
          "kana": "がくぎょう",
          "romaji": "gakugyou",
          "pos": "名",
          "zh": "學業",
          "ex": "彼（かれ）はアルバイトと学業（がくぎょう）を両立（りょうりつ）させるのに苦労（くろう）している。",
          "ex_zh": "他為了兼顧打工與學業而吃盡苦頭。"
        },
        {
          "word": "学殖",
          "kana": "がくしょく",
          "romaji": "gakushoku",
          "pos": "名",
          "zh": "學識；學問造詣",
          "ex": "あの教授（きょうじゅ）の学殖（がくしょく）の深（ふか）さには誰（だれ）もが敬服（けいふく）する。",
          "ex_zh": "那位教授學識淵博之深令人人敬佩。"
        },
        {
          "word": "学派",
          "kana": "がくは",
          "romaji": "gakuha",
          "pos": "名",
          "zh": "學派",
          "ex": "この理論（りろん）は従来（じゅうらい）の学派（がくは）とは一線（いっせん）を画（かく）している。",
          "ex_zh": "這個理論與以往的學派劃清了界線。"
        },
        {
          "word": "学際",
          "kana": "がくさい",
          "romaji": "gakusai",
          "pos": "名",
          "zh": "跨學科；科際",
          "ex": "この研究（けんきゅう）は複数（ふくすう）の分野（ぶんや）にまたがる学際的（がくさいてき）な取（と）り組（く）みだ。",
          "ex_zh": "這項研究是跨越多個領域的跨學科嘗試。"
        },
        {
          "word": "幻覚",
          "kana": "げんかく",
          "romaji": "genkaku",
          "pos": "名",
          "zh": "幻覺",
          "ex": "極度（きょくど）の疲労（ひろう）から幻覚（げんかく）を見（み）ることがあるという。",
          "ex_zh": "據說極度疲勞有時會產生幻覺。"
        },
        {
          "word": "強迫観念",
          "kana": "きょうはくかんねん",
          "romaji": "kyouhakukannen",
          "pos": "名",
          "zh": "強迫觀念",
          "ex": "何度（なんど）も手（て）を洗（あら）わなければ気（き）が済（す）まないという強迫観念（きょうはくかんねん）に苦（くる）しむ。",
          "ex_zh": "飽受非得反覆洗手不可的強迫觀念所苦。"
        },
        {
          "word": "感化",
          "kana": "かんか",
          "romaji": "kanka",
          "pos": "名／動III",
          "zh": "感化",
          "ex": "恩師（おんし）の言葉（ことば）に感化（かんか）されて教育（きょういく）の道（みち）を志（こころざ）した。",
          "ex_zh": "受到恩師話語的感化,立志走上教育這條路。"
        },
        {
          "word": "投影",
          "kana": "とうえい",
          "romaji": "touei",
          "pos": "名／動III",
          "zh": "投影；(心理)投射",
          "ex": "彼（かれ）の作品（さくひん）には幼年期（ようねんき）の記憶（きおく）が色濃（いろこ）く投影（とうえい）されている。",
          "ex_zh": "他的作品濃厚地投射出幼年時期的記憶。"
        },
        {
          "word": "教諭",
          "kana": "きょうゆ",
          "romaji": "kyouyu",
          "pos": "名",
          "zh": "(中小學)教師",
          "ex": "彼女（かのじょ）は今春（こんしゅん）から中学校（ちゅうがっこう）の教諭（きょうゆ）として働（はたら）く。",
          "ex_zh": "她從今年春天開始以國中教師的身分工作。"
        },
        {
          "word": "欲求",
          "kana": "よっきゅう",
          "romaji": "yokkyuu",
          "pos": "名／動III",
          "zh": "欲求；慾望",
          "ex": "人間（にんげん）には承認（しょうにん）されたいという欲求（よっきゅう）が存在（そんざい）する。",
          "ex_zh": "人類存在著渴望被認同的慾望。"
        },
        {
          "word": "深層心理",
          "kana": "しんそうしんり",
          "romaji": "shinsoushinri",
          "pos": "名",
          "zh": "深層心理",
          "ex": "この小説（しょうせつ）は登場人物（とうじょうじんぶつ）の深層心理（しんそうしんり）を巧（たく）みに描（えが）いている。",
          "ex_zh": "這部小說巧妙地描寫了登場人物的深層心理。"
        },
        {
          "word": "潜在意識",
          "kana": "せんざいいしき",
          "romaji": "senzaiishiki",
          "pos": "名",
          "zh": "潛意識",
          "ex": "広告（こうこく）は消費者（しょうひしゃ）の潜在意識（せんざいいしき）に働（はたら）きかけるよう設計（せっけい）されている。",
          "ex_zh": "廣告的設計是為了作用於消費者的潛意識。"
        },
        {
          "word": "無意識",
          "kana": "むいしき",
          "romaji": "muishiki",
          "pos": "名",
          "zh": "無意識；下意識",
          "ex": "彼（かれ）は無意識（むいしき）のうちに貧乏揺（びんぼうゆ）すりをしていた。",
          "ex_zh": "他不自覺地一直在抖腳。"
        },
        {
          "word": "独善",
          "kana": "どくぜん",
          "romaji": "dokuzen",
          "pos": "名",
          "zh": "獨善；自以為是",
          "ex": "彼（かれ）のやり方（かた）は独善的（どくぜんてき）だと周囲（しゅうい）から批判（ひはん）されている。",
          "ex_zh": "他的做法被周圍的人批評為獨善其身。"
        },
        {
          "word": "独断",
          "kana": "どくだん",
          "romaji": "dokudan",
          "pos": "名／動III",
          "zh": "獨斷；武斷",
          "ex": "上司（じょうし）は部下（ぶか）の意見（いけん）を聞（き）かず、独断（どくだん）で計画（けいかく）を進（すす）めた。",
          "ex_zh": "上司沒有聽取部下的意見,獨斷地推動了計畫。"
        },
        {
          "word": "異説",
          "kana": "いせつ",
          "romaji": "isetsu",
          "pos": "名",
          "zh": "異說；不同見解",
          "ex": "この事件（じけん）の真相（しんそう）については異説（いせつ）も少（すく）なくない。",
          "ex_zh": "關於這起事件的真相,異說也不少。"
        },
        {
          "word": "省察",
          "kana": "せいさつ",
          "romaji": "seisatsu",
          "pos": "名／動III",
          "zh": "省察；反省",
          "ex": "一日（いちにち）の終（お）わりに自（みずか）らの言動（げんどう）を省察（せいさつ）する習慣（しゅうかん）がある。",
          "ex_zh": "有在一天結束時省察自己言行的習慣。"
        },
        {
          "word": "碩学",
          "kana": "せきがく",
          "romaji": "sekigaku",
          "pos": "名",
          "zh": "碩學；學識淵博之人",
          "ex": "東洋哲学（とうようてつがく）の碩学（せきがく）として知（し）られる先生（せんせい）に教（おそ）わった。",
          "ex_zh": "曾受教於以東洋哲學泰斗聞名的老師。"
        },
        {
          "word": "私塾",
          "kana": "しじゅく",
          "romaji": "shijuku",
          "pos": "名",
          "zh": "私塾",
          "ex": "江戸時代（えどじだい）、多（おお）くの若者（わかもの）が私塾（しじゅく）で学問（がくもん）に励（はげ）んだ。",
          "ex_zh": "江戶時代,許多年輕人在私塾裡勤學不倦。"
        },
        {
          "word": "究明",
          "kana": "きゅうめい",
          "romaji": "kyuumei",
          "pos": "名／動III",
          "zh": "究明；查明",
          "ex": "事故（じこ）の原因究明（げんいんきゅうめい）には長（なが）い時間（じかん）がかかる見通（みとお）しだ。",
          "ex_zh": "預計釐清事故原因需要很長的時間。"
        },
        {
          "word": "練達",
          "kana": "れんたつ",
          "romaji": "rentatsu",
          "pos": "名",
          "zh": "熟練；老練",
          "ex": "練達（れんたつ）の域（いき）に達（たっ）するまでには地道（じみち）な努力（どりょく）の積（つ）み重（かさ）ねが要（い）る。",
          "ex_zh": "要達到熟練的境界,需要腳踏實地努力的積累。"
        },
        {
          "word": "自己嫌悪",
          "kana": "じこけんお",
          "romaji": "jikoken'o",
          "pos": "名",
          "zh": "自我厭惡",
          "ex": "約束（やくそく）を破（やぶ）ってしまい、激（はげ）しい自己嫌悪（じこけんお）に陥（おちい）った。",
          "ex_zh": "因為食言而陷入強烈的自我厭惡。"
        },
        {
          "word": "自己暗示",
          "kana": "じこあんじ",
          "romaji": "jikoanji",
          "pos": "名",
          "zh": "自我暗示",
          "ex": "「大丈夫（だいじょうぶ）だ」と繰（く）り返（かえ）し唱（とな）えることは一種（いっしゅ）の自己暗示（じこあんじ）だ。",
          "ex_zh": "反覆念著「沒問題的」是一種自我暗示。"
        },
        {
          "word": "自己陶酔",
          "kana": "じことうすい",
          "romaji": "jikotousui",
          "pos": "名",
          "zh": "自我陶醉",
          "ex": "彼（かれ）のスピーチは自己陶酔（じことうすい）に陥（おちい）っているように感（かん）じられた。",
          "ex_zh": "他的演講讓人覺得陷入了自我陶醉之中。"
        },
        {
          "word": "自戒",
          "kana": "じかい",
          "romaji": "jikai",
          "pos": "名／動III",
          "zh": "自我警惕；自誡",
          "ex": "同（おな）じ過（あやま）ちを繰（く）り返（かえ）さないよう、常（つね）に自戒（じかい）している。",
          "ex_zh": "為了不重蹈覆轍,總是自我警惕。"
        },
        {
          "word": "薫陶",
          "kana": "くんとう",
          "romaji": "kuntou",
          "pos": "名",
          "zh": "薰陶",
          "ex": "幼少期（ようしょうき）に受（う）けた恩師（おんし）の薫陶（くんとう）が今（いま）も彼（かれ）を支（ささ）えている。",
          "ex_zh": "幼年時期受到恩師的薰陶,至今仍支撐著他。"
        },
        {
          "word": "触発",
          "kana": "しょくはつ",
          "romaji": "shokuhatsu",
          "pos": "名／動III",
          "zh": "觸發；啟發",
          "ex": "恩師（おんし）の一言（ひとこと）に触発（しょくはつ）されて研究（けんきゅう）の道（みち）に進（すす）むことを決（き）めた。",
          "ex_zh": "受到恩師一句話的觸動,決定走上研究這條路。"
        },
        {
          "word": "訓育",
          "kana": "くんいく",
          "romaji": "kun'iku",
          "pos": "名／動III",
          "zh": "訓育；品德教育",
          "ex": "学校（がっこう）は知識（ちしき）だけでなく人格（じんかく）の訓育（くんいく）にも力（ちから）を入（い）れるべきだ。",
          "ex_zh": "學校不僅該傳授知識,也應致力於人格的陶冶教育。"
        },
        {
          "word": "退学",
          "kana": "たいがく",
          "romaji": "taigaku",
          "pos": "名／動III",
          "zh": "退學",
          "ex": "度重（たびかさ）なる問題行動（もんだいこうどう）の末（すえ）、彼（かれ）は退学処分（たいがくしょぶん）を受（う）けた。",
          "ex_zh": "經過多次的問題行為之後,他被處以退學處分。"
        },
        {
          "word": "逃避",
          "kana": "とうひ",
          "romaji": "touhi",
          "pos": "名／動III",
          "zh": "逃避",
          "ex": "現実（げんじつ）から逃避（とうひ）しても問題（もんだい）は何（なに）も解決（かいけつ）しない。",
          "ex_zh": "即使逃避現實,問題也不會有任何解決。"
        },
        {
          "word": "過敏",
          "kana": "かびん",
          "romaji": "kabin",
          "pos": "な形",
          "zh": "過敏；過度敏感",
          "ex": "彼（かれ）は他人（たにん）の評価（ひょうか）に過敏（かびん）に反応（はんのう）しすぎる傾向（けいこう）がある。",
          "ex_zh": "他有對他人評價過度敏感反應的傾向。"
        },
        {
          "word": "門下生",
          "kana": "もんかせい",
          "romaji": "monkasei",
          "pos": "名",
          "zh": "門生；弟子",
          "ex": "彼（かれ）は高名（こうめい）な陶芸家（とうげいか）の門下生（もんかせい）として修業（しゅぎょう）を積（つ）んだ。",
          "ex_zh": "他曾以知名陶藝家門下弟子的身分累積修業經歷。"
        },
        {
          "word": "陶冶",
          "kana": "とうや",
          "romaji": "touya",
          "pos": "名／動III",
          "zh": "陶冶(性情、人格)",
          "ex": "芸術教育（げいじゅつきょういく）は人格（じんかく）の陶冶（とうや）に大（おお）きく寄与（きよ）する。",
          "ex_zh": "藝術教育對人格的陶冶有很大的貢獻。"
        }
      ]
    },
    {
      "category": "名詞：文化・芸術・宗教・報道メディア（N1補充）",
      "entries": [
        {
          "word": "儀礼",
          "kana": "ぎれい",
          "romaji": "girei",
          "pos": "名",
          "zh": "禮儀；儀式",
          "ex": "結婚式（けっこんしき）には、地域（ちいき）ごとに独自（どくじ）の儀礼（ぎれい）が受（う）け継（つ）がれている。",
          "ex_zh": "婚禮上，各地都傳承著各自獨特的禮儀。"
        },
        {
          "word": "祭祀",
          "kana": "さいし",
          "romaji": "saishi",
          "pos": "名",
          "zh": "祭祀",
          "ex": "一族（いちぞく）は毎年（まいとし）、祖先（そせん）を祀（まつ）る祭祀（さいし）を欠（か）かさず行（おこな）ってきた。",
          "ex_zh": "這個家族每年都不間斷地舉行祭祀祖先的儀式。"
        },
        {
          "word": "古典",
          "kana": "こてん",
          "romaji": "koten",
          "pos": "名",
          "zh": "古典；古典作品",
          "ex": "彼（かれ）は古典（こてん）文学（ぶんがく）に精通（せいつう）し、原文（げんぶん）で読（よ）みこなす。",
          "ex_zh": "他精通古典文學，能夠直接閱讀原文。"
        },
        {
          "word": "隆盛",
          "kana": "りゅうせい",
          "romaji": "ryuusei",
          "pos": "名",
          "zh": "興盛；隆盛",
          "ex": "江戸時代（えどじだい）、歌舞伎（かぶき）は庶民文化（しょみんぶんか）として隆盛（りゅうせい）を極（きわ）めた。",
          "ex_zh": "江戶時代，歌舞伎作為庶民文化盛極一時。"
        },
        {
          "word": "風土",
          "kana": "ふうど",
          "romaji": "fuudo",
          "pos": "名",
          "zh": "風土",
          "ex": "その土地（とち）に特有（とくゆう）の風土（ふうど）が、独特（どくとく）な陶芸（とうげい）の作風（さくふう）を育（はぐく）んだ。",
          "ex_zh": "那片土地特有的風土，孕育出獨特的陶藝風格。"
        },
        {
          "word": "土着",
          "kana": "どちゃく",
          "romaji": "dochaku",
          "pos": "名",
          "zh": "土著；本地固有",
          "ex": "この儀式（ぎしき）は、仏教伝来以前（ぶっきょうでんらいいぜん）からの土着（どちゃく）信仰（しんこう）に由来（ゆらい）する。",
          "ex_zh": "這個儀式源自佛教傳入之前的本土信仰。"
        },
        {
          "word": "文化財",
          "kana": "ぶんかざい",
          "romaji": "bunkazai",
          "pos": "名",
          "zh": "文化財產；文物",
          "ex": "老朽化（ろうきゅうか）した社殿（しゃでん）が国（くに）の重要文化財（じゅうようぶんかざい）に指定（してい）された。",
          "ex_zh": "老舊的神殿被指定為國家重要文化財。"
        },
        {
          "word": "伝統芸能",
          "kana": "でんとうげいのう",
          "romaji": "dentougeinou",
          "pos": "名",
          "zh": "傳統藝能",
          "ex": "能楽（のうがく）は日本（にほん）を代表（だいひょう）する伝統芸能（でんとうげいのう）の一（ひと）つだ。",
          "ex_zh": "能樂是代表日本的傳統藝能之一。"
        },
        {
          "word": "典雅",
          "kana": "てんが",
          "romaji": "tenga",
          "pos": "な形",
          "zh": "典雅；高雅",
          "ex": "能舞台（のうぶたい）に漂（ただよ）う典雅（てんが）な雰囲気（ふんいき）に、観客（かんきゃく）は息（いき）をのんだ。",
          "ex_zh": "能劇舞台上瀰漫的典雅氣氛，令觀眾屏息。"
        },
        {
          "word": "風雅",
          "kana": "ふうが",
          "romaji": "fuuga",
          "pos": "名",
          "zh": "風雅；風流雅致",
          "ex": "松尾芭蕉（まつおばしょう）は俳諧（はいかい）に風雅（ふうが）の理想（りそう）を求（もと）め続（つづ）けた。",
          "ex_zh": "松尾芭蕉在俳諧中不斷追求風雅的理想。"
        },
        {
          "word": "後継者",
          "kana": "こうけいしゃ",
          "romaji": "koukeisha",
          "pos": "名",
          "zh": "繼承人；接班人",
          "ex": "名匠（めいしょう）の技（わざ）を継（つ）ぐ後継者（こうけいしゃ）が不足（ふそく）している。",
          "ex_zh": "繼承名匠技藝的接班人正日益短缺。"
        },
        {
          "word": "由緒",
          "kana": "ゆいしょ",
          "romaji": "yuisho",
          "pos": "名",
          "zh": "由來；淵源",
          "ex": "この神社（じんじゃ）は千年（せんねん）を超（こ）える由緒（ゆいしょ）を誇（ほこ）る。",
          "ex_zh": "這座神社擁有超過千年的悠久淵源。"
        },
        {
          "word": "異端",
          "kana": "いたん",
          "romaji": "itan",
          "pos": "名",
          "zh": "異端",
          "ex": "彼（かれ）の画風（がふう）は当時（とうじ）、美術界（びじゅつかい）の異端（いたん）と見（み）なされていた。",
          "ex_zh": "他的畫風在當時被視為美術界的異端。"
        },
        {
          "word": "名匠",
          "kana": "めいしょう",
          "romaji": "meishou",
          "pos": "名",
          "zh": "名匠；大師",
          "ex": "若（わか）き陶芸家（とうげいか）は名匠（めいしょう）の下（もと）で十年間（じゅうねんかん）修行（しゅぎょう）を積（つ）んだ。",
          "ex_zh": "年輕的陶藝家在名匠門下修行了十年。"
        },
        {
          "word": "力作",
          "kana": "りきさく",
          "romaji": "rikisaku",
          "pos": "名",
          "zh": "力作；用心之作",
          "ex": "三年（さんねん）の歳月（さいげつ）をかけた力作（りきさく）が、ついに展覧会（てんらんかい）に出品（しゅっぴん）された。",
          "ex_zh": "耗費三年心血的力作，終於在展覽會上展出。"
        },
        {
          "word": "鑑識眼",
          "kana": "かんしきがん",
          "romaji": "kanshikigan",
          "pos": "名",
          "zh": "鑑賞力；識別眼光",
          "ex": "骨董商（こっとうしょう）としての鑑識眼（かんしきがん）は、長年（ながねん）の経験（けいけん）で培（つちか）われた。",
          "ex_zh": "身為古董商的鑑識眼光，是靠多年經驗培養而成。"
        },
        {
          "word": "評伝",
          "kana": "ひょうでん",
          "romaji": "hyouden",
          "pos": "名",
          "zh": "評傳",
          "ex": "作家（さっか）の生涯（しょうがい）を追（お）った評伝（ひょうでん）が話題（わだい）を呼（よ）んでいる。",
          "ex_zh": "追溯這位作家生涯的評傳引發了話題。"
        },
        {
          "word": "美意識",
          "kana": "びいしき",
          "romaji": "biishiki",
          "pos": "名",
          "zh": "審美意識；美感",
          "ex": "余白（よはく）を生（い）かす日本独自（にほんどくじ）の美意識（びいしき）が、水墨画（すいぼくが）に表（あらわ）れている。",
          "ex_zh": "善用留白的日本獨特審美意識，體現在水墨畫之中。"
        },
        {
          "word": "造形",
          "kana": "ぞうけい",
          "romaji": "zoukei",
          "pos": "名",
          "zh": "造型",
          "ex": "彼（かれ）の彫刻（ちょうこく）は、有機的（ゆうきてき）な造形（ぞうけい）が特徴（とくちょう）だ。",
          "ex_zh": "他的雕刻以有機的造型為特色。"
        },
        {
          "word": "振付",
          "kana": "ふりつけ",
          "romaji": "furitsuke",
          "pos": "名",
          "zh": "舞蹈編排；編舞",
          "ex": "有名（ゆうめい）な振付師（ふりつけし）が新作（しんさく）バレエの振付（ふりつけ）を手（て）がけた。",
          "ex_zh": "知名編舞師負責了這齣新芭蕾舞劇的編舞。"
        },
        {
          "word": "熱演",
          "kana": "ねつえん",
          "romaji": "netsuen",
          "pos": "名／動III",
          "zh": "精彩演出；賣力演出",
          "ex": "主演女優（しゅえんじょゆう）の熱演（ねつえん）に、観客（かんきゃく）は涙（なみだ）を誘（さそ）われた。",
          "ex_zh": "女主角的精彩演出讓觀眾不禁落淚。"
        },
        {
          "word": "競演",
          "kana": "きょうえん",
          "romaji": "kyouen",
          "pos": "名／動III",
          "zh": "競演；同台較量演出",
          "ex": "若手（わかて）とベテランが同（おな）じ舞台（ぶたい）で競演（きょうえん）し、火花（ひばな）を散（ち）らした。",
          "ex_zh": "新秀與資深演員在同一舞台上競演，激起了火花。"
        },
        {
          "word": "朗詠",
          "kana": "ろうえい",
          "romaji": "rouei",
          "pos": "名／動III",
          "zh": "吟詠；朗誦（詩歌）",
          "ex": "宴（うたげ）の席（せき）で、漢詩（かんし）を朗詠（ろうえい）する声（こえ）が響（ひび）き渡（わた）った。",
          "ex_zh": "宴席上，吟詠漢詩的聲音迴盪四方。"
        },
        {
          "word": "説話",
          "kana": "せつわ",
          "romaji": "setsuwa",
          "pos": "名",
          "zh": "民間故事；傳說（說話文學）",
          "ex": "『今昔物語集（こんじゃくものがたりしゅう）』は日本最大級（にほんさいだいきゅう）の説話集（せつわしゅう）として知（し）られる。",
          "ex_zh": "《今昔物語集》以日本規模最大的說話集而聞名。"
        },
        {
          "word": "秘話",
          "kana": "ひわ",
          "romaji": "hiwa",
          "pos": "名",
          "zh": "秘聞；不為人知的內幕",
          "ex": "映画（えいが）の撮影現場（さつえいげんば）にまつわる秘話（ひわ）が、番組（ばんぐみ）で明（あき）らかにされた。",
          "ex_zh": "節目揭露了與電影拍攝現場相關的祕聞。"
        },
        {
          "word": "文才",
          "kana": "ぶんさい",
          "romaji": "bunsai",
          "pos": "名",
          "zh": "文才",
          "ex": "幼少（ようしょう）の頃（ころ）から文才（ぶんさい）に恵（めぐ）まれ、十代（じゅうだい）で小説（しょうせつ）を発表（はっぴょう）した。",
          "ex_zh": "他自幼便才華洋溢，十幾歲時就發表了小說。"
        },
        {
          "word": "語彙",
          "kana": "ごい",
          "romaji": "goi",
          "pos": "名",
          "zh": "詞彙",
          "ex": "古典文学（こてんぶんがく）を読（よ）み込（こ）むことで、語彙（ごい）が飛躍的（ひやくてき）に増（ふ）えた。",
          "ex_zh": "透過深入研讀古典文學，詞彙量有了飛躍性的增長。"
        },
        {
          "word": "修辞",
          "kana": "しゅうじ",
          "romaji": "shuuji",
          "pos": "名",
          "zh": "修辭",
          "ex": "この詩人（しじん）は巧（たく）みな修辞（しゅうじ）を駆使（くし）して、情景（じょうけい）を鮮（あざ）やかに描（えが）き出（だ）す。",
          "ex_zh": "這位詩人巧妙運用修辭手法，將情景描繪得栩栩如生。"
        },
        {
          "word": "隠喩",
          "kana": "いんゆ",
          "romaji": "in'yu",
          "pos": "名",
          "zh": "隱喻",
          "ex": "この小説（しょうせつ）には、人生（じんせい）を旅（たび）に喩（たと）える隠喩（いんゆ）が随所（ずいしょ）に見（み）られる。",
          "ex_zh": "這部小說隨處可見將人生比喻為旅程的隱喻。"
        },
        {
          "word": "往生",
          "kana": "おうじょう",
          "romaji": "oujou",
          "pos": "名／動III",
          "zh": "往生；（佛教）逝世；（俗）吃盡苦頭",
          "ex": "祖母（そぼ）は「畳（たたみ）の上（うえ）で往生（おうじょう）したい」と常々（つねづね）語（かた）っていた。",
          "ex_zh": "祖母經常說「希望能安詳地在家中往生」。"
        },
        {
          "word": "成仏",
          "kana": "じょうぶつ",
          "romaji": "joubutsu",
          "pos": "名／動III",
          "zh": "成佛；往生",
          "ex": "僧侶（そうりょ）は読経（どきょう）を通（つう）じて、故人（こじん）の成仏（じょうぶつ）を祈（いの）った。",
          "ex_zh": "僧侶透過誦經，祈求亡者能夠成佛。"
        },
        {
          "word": "解脱",
          "kana": "げだつ",
          "romaji": "gedatsu",
          "pos": "名／動III",
          "zh": "解脫",
          "ex": "仏教（ぶっきょう）では、煩悩（ぼんのう）を断（た）ち切（き）ることで解脱（げだつ）に至（いた）るとされる。",
          "ex_zh": "佛教認為，斷除煩惱便能達到解脫。"
        },
        {
          "word": "功徳",
          "kana": "くどく",
          "romaji": "kudoku",
          "pos": "名",
          "zh": "功德",
          "ex": "困（こま）っている人（ひと）を助（たす）けることは、大（おお）きな功徳（くどく）を積（つ）む行為（こうい）とされる。",
          "ex_zh": "幫助有困難的人被認為是積累大功德的行為。"
        },
        {
          "word": "御利益",
          "kana": "ごりやく",
          "romaji": "goriyaku",
          "pos": "名",
          "zh": "神佛保佑；靈驗",
          "ex": "この神社（じんじゃ）は縁結（えんむす）びの御利益（ごりやく）があるとされ、若者（わかもの）に人気（にんき）だ。",
          "ex_zh": "這座神社據說有結緣的神佛保佑，深受年輕人歡迎。"
        },
        {
          "word": "神託",
          "kana": "しんたく",
          "romaji": "shintaku",
          "pos": "名",
          "zh": "神諭",
          "ex": "古代（こだい）の王（おう）は、重要（じゅうよう）な決断（けつだん）を下（くだ）す前（まえ）に神託（しんたく）を仰（あお）いだ。",
          "ex_zh": "古代的君王在做出重要決斷前，會祈求神諭。"
        },
        {
          "word": "神事",
          "kana": "しんじ",
          "romaji": "shinji",
          "pos": "名",
          "zh": "祭神儀式；神事",
          "ex": "この祭（まつ）りは、五穀豊穣（ごこくほうじょう）を祈（いの）る神事（しんじ）として千年以上（せんねんいじょう）続（つづ）いている。",
          "ex_zh": "這個祭典作為祈求五穀豐收的神事，已延續超過千年。"
        }
      ]
    }
  ]
}
